{
  "teamName": "Platform Team",
  "apis": [
    {
      "apiName": "User Management API",
      "assetId": "user-mgmt-api-v1",
      "apiOwner": "john.doe@company.com",
      "teamName": "Platform Team",
      "apiOwnerEmail": "john.doe@company.com",
      "munitExempt": false,
      "customCoverage": null,
      "businessGroups": ["Core Platform"],
      "lastUpdated": "2025-01-17T18:20:00Z"
    },
    {
      "apiName": "Authentication Service",
      "assetId": "auth-service-v2",
      "apiOwner": "jane.smith@company.com",
      "teamName": "Platform Team",
      "apiOwnerEmail": "jane.smith@company.com",
      "munitExempt": true,
      "customCoverage": 85,
      "businessGroups": ["Core Platform"],
      "lastUpdated": "2025-01-17T18:20:00Z"
    }
  ]
} 